idem_sources/conf.py
idem_sources/version.py
idem_sources/acct/git/init.py
idem_sources/source/gitfs_sls.py
idem_sources-2.0.0.dist-info/LICENSE
idem_sources-2.0.0.dist-info/METADATA
idem_sources-2.0.0.dist-info/WHEEL
idem_sources-2.0.0.dist-info/top_level.txt
idem_sources-2.0.0.dist-info/RECORD
