Metadata-Version: 2.1
Name: idem-sources
Version: 2.0.0
Summary: Generic sls-source plugins for idem
Home-page: 
Author: Tyler Johnson
Author-email: tyjohnson@vmware.com
Classifier: Environment :: Console
Classifier: Intended Audience :: Developers
Classifier: Intended Audience :: Information Technology
Classifier: Intended Audience :: System Administrators
Classifier: Operating System :: OS Independent
Classifier: Programming Language :: Python
Classifier: Programming Language :: Python :: 3.8
Classifier: Programming Language :: Python :: 3.9
Classifier: Programming Language :: Python :: 3.10
Classifier: Programming Language :: Python :: 3.11
Classifier: Development Status :: 5 - Production/Stable
Requires-Python: >=3.8
License-File: LICENSE
Requires-Dist: idem >=25.0.1
Requires-Dist: pop
Requires-Dist: acct
Requires-Dist: GitPython >=3.1.27
